xcsv/__init__.py
xcsv-0.6.3.dist-info/LICENSE
xcsv-0.6.3.dist-info/WHEEL
xcsv-0.6.3.dist-info/METADATA
xcsv-0.6.3.dist-info/RECORD
