Metadata-Version: 2.1
Name: xcsv
Version: 0.6.3
Summary: Package for working with extended CSV (XCSV) files
Home-page: https://github.com/paul-breen/xcsv
License: Apache-2.0
Author: Paul Breen
Author-email: pbree@bas.ac.uk
Requires-Python: >=3.8,<4.0
Classifier: License :: OSI Approved :: Apache Software License
Classifier: Programming Language :: Python :: 3
Classifier: Programming Language :: Python :: 3.8
Classifier: Programming Language :: Python :: 3.9
Classifier: Programming Language :: Python :: 3.10
Classifier: Programming Language :: Python :: 3.11
Requires-Dist: pandas (>=2.0.0,<3.0.0)
Project-URL: Documentation, https://paul-breen.github.io/xcsv/
Project-URL: Repository, https://github.com/paul-breen/xcsv
